tutor_contrib_aspects-2.5.0.dist-info/licenses/LICENSE
tutoraspects/__about__.py
tutoraspects/__init__.py
tutoraspects/asset_command_helpers.py
tutoraspects/commands_v1.py
tutoraspects/filters.py
tutoraspects/plugin.py
tutoraspects/utils.py
tutoraspects/patches/.gitignore
tutoraspects/patches/caddyfile
tutoraspects/patches/clickhouse-extra-sql
tutoraspects/patches/clickhouse-server-config
tutoraspects/patches/clickhouse-user-config
tutoraspects/patches/k8s-deployments
tutoraspects/patches/k8s-jobs
tutoraspects/patches/k8s-services
tutoraspects/patches/k8s-volumes
tutoraspects/patches/kustomization-configmapgenerator
tutoraspects/patches/local-docker-compose-dev-services
tutoraspects/patches/local-docker-compose-jobs-services
tutoraspects/patches/local-docker-compose-permissions-command
tutoraspects/patches/local-docker-compose-permissions-volumes
tutoraspects/patches/local-docker-compose-services
tutoraspects/patches/mfe-dockerfile-post-npm-install-authoring
tutoraspects/patches/mfe-env-config-runtime-definitions-authoring
tutoraspects/patches/openedx-common-settings
tutoraspects/patches/openedx-dev-dockerfile-post-python-requirements
tutoraspects/patches/openedx-development-settings
tutoraspects/patches/openedx-dockerfile-post-python-requirements
tutoraspects/patches/superset-extra-asset-translations
tutoraspects/patches/superset-extra-assets
tutoraspects/patches/superset-extra-roles
tutoraspects/patches/superset-jinja-filters
tutoraspects/patches/superset-row-level-security
tutoraspects/patches/superset-sso-assignment-rules
tutoraspects/patches/xapi-db-load-config-yaml
tutoraspects/templates/base-docker-compose-services
tutoraspects/templates/aspects/apps/.gitignore
tutoraspects/templates/aspects/apps/aspects/dbt/profiles.yml
tutoraspects/templates/aspects/apps/aspects/migrations/README.rst
tutoraspects/templates/aspects/apps/aspects/migrations/alembic.ini
tutoraspects/templates/aspects/apps/aspects/migrations/alembic/env.py
tutoraspects/templates/aspects/apps/aspects/migrations/alembic/script.py.mako
tutor_contrib_aspects-2.5.0.dist-info/METADATA
tutor_contrib_aspects-2.5.0.dist-info/WHEEL
tutor_contrib_aspects-2.5.0.dist-info/entry_points.txt
tutor_contrib_aspects-2.5.0.dist-info/top_level.txt
tutor_contrib_aspects-2.5.0.dist-info/RECORD
