Metadata-Version: 2.4
Name: tutor-contrib-aspects
Version: 2.5.0
Summary: Aspects plugin for Tutor
Home-page: https://github.com/openedx/tutor-contrib-aspects
Author: The Open edX Community
License: Apache 2.0
Project-URL: Code, https://github.com/openedx/tutor-contrib-aspects
Project-URL: Issue tracker, https://github.com/openedx/tutor-contrib-aspects/issues
Classifier: Development Status :: 3 - Alpha
Classifier: Intended Audience :: Developers
Classifier: License :: OSI Approved :: Apache Software License
Classifier: Operating System :: OS Independent
Classifier: Programming Language :: Python
Classifier: Programming Language :: Python :: 3.11
Classifier: Programming Language :: Python :: 3.12
Requires-Python: >=3.11
License-File: LICENSE
Requires-Dist: bcrypt
Requires-Dist: click<8.3.0,>=8.0
Requires-Dist: importlib-resources
Requires-Dist: openedx-atlas
Requires-Dist: ruamel.yaml
Requires-Dist: shandy-sqlfmt[jinjafmt]==0.26.0
Requires-Dist: tutor>=18
Requires-Dist: tutor-mfe>=18
Dynamic: author
Dynamic: classifier
Dynamic: description
Dynamic: description-content-type
Dynamic: home-page
Dynamic: license
Dynamic: license-file
Dynamic: project-url
Dynamic: requires-dist
Dynamic: requires-python
Dynamic: summary
